qif2ofx/__init__.py
qif2ofx/qif.py
qif2ofx/qif2ofx.py
qif2ofx-0.0.3.data/scripts/qif2ofx
qif2ofx-0.0.3.dist-info/LICENSE
qif2ofx-0.0.3.dist-info/METADATA
qif2ofx-0.0.3.dist-info/WHEEL
qif2ofx-0.0.3.dist-info/top_level.txt
qif2ofx-0.0.3.dist-info/RECORD
