Metadata-Version: 2.1
Name: qif2ofx
Version: 0.0.3
Summary: Convert from QIF to OXF
Home-page: https://github.com/talkdirty/qif2ofx
Author: Georg Grab
Author-email: git@georggrab.net
License: UNKNOWN
Platform: UNKNOWN
Classifier: Programming Language :: Python :: 3
Classifier: License :: OSI Approved :: MIT License
Classifier: Operating System :: OS Independent
Requires-Python: >=3.6
Requires-Dist: ofxtools
